[
    {
        "id": "ps-001",
        "title": "খৎনা করাতে গিয়ে ইনফেকশন! ডাঃ মোহাম্মদ ফরিদুল ইসলামের অসাধারণ চিকিৎসায় ছেলের জীবন বাঁচল",
        "patient_name": "Children of Mohammad Hasan",
        "city": "Cox's Bazar",
        "doctor_name": "Dr. Muhammad Faridul Islam",
        "speciality": "Paediatric Surgery & Paediatric Urology",
        "published_date": "06 January 2026",
        "image": "https://images.unsplash.com/photo-1516627145497-ae6968895b74?q=80&w=800",
        "content": "কক্সবাজারের মোহাম্মদ হাসান তার বাচ্চাকে ব্যথাহীন সুন্নতে খৎনা করাতে নিয়ে যান স্থানীয় হাসপাতালে। কিন্তু সেখানেই শুরু হয় বিপত্তি। ক্ষত শুকানো তো দূরে থাক, বরং সেখানে হয়ে যায় ইনফেকশন। সঠিক চিকিৎসকের অভাবে পরবর্তীতে চিকিৎসাও দিতে পারছিলেন না। এরপরই তিনি এভারকেয়ার চট্টগ্রামের সুনাম মনে করে তার বাচ্চাকে নিয়ে আসেন এবং শরণাপন্ন হন এটেন্ডিং কনসালটেন্ট ড. মোহাম্মদ ফরিদুল ইসলাম (পেডিয়াট্রিক সার্জন)-এর। বর্তমানে শিশুটি ইনফেকশন কাটিয়ে জটিল অপারেশন শেষে সুস্থ হয়ে উঠেছে।",
        "video_url": "https://youtube.com/watch?v=example1"
    },
    {
        "id": "ps-002",
        "title": "সঠিক সময়ে হার্ট সার্জারি ফিরিয়ে দিলো নতুন জীবন",
        "patient_name": "Mrs. Saleha Begum",
        "city": "Chittagong",
        "doctor_name": "Dr. Zahir Al-Amin",
        "speciality": "Cardiology",
        "published_date": "15 January 2026",
        "image": "https://images.unsplash.com/photo-1581056771107-24ca5f033842?q=80&w=800",
        "content": "দীর্ঘদিন ধরে বুকে ব্যথা ও শ্বাসকষ্টে ভুগছিলেন সালেহা বেগম। পরীক্ষা-নিরীক্ষার পর ধরা পড়ে তার হার্টে তিনটি ব্লক। এভারকেয়ারের কার্ডিওলজি টিমের দক্ষতায় তার সফল বাইপাস সার্জারি সম্পন্ন হয়। অপারেশনের মাত্র ৫ দিন পর তিনি সুস্থ অবস্থায় বাড়ি ফেরেন এবং এখন স্বাভাবিক জীবনযাপন করছেন।",
        "video_url": ""
    },
    {
        "id": "ps-003",
        "title": "প্যারালাইসিস থেকে মুক্তি: নিউরো-রিহ্যাবিলিটেশনের এক অনন্য জয়",
        "patient_name": "Mr. Rafiqul Islam",
        "city": "Feni",
        "doctor_name": "Neurology Department Team",
        "speciality": "Neurology & Rehabilitation",
        "published_date": "20 January 2026",
        "image": "https://images.unsplash.com/photo-1516549655169-df83a0774514?q=80&w=800",
        "content": "হঠাৎ স্ট্রোকে আক্রান্ত হয়ে শরীরের বাম পাশ অবশ হয়ে গিয়েছিল রফিকুল সাহেবের। এভারকেয়ারের ইমার্জেন্সি টিমের দ্রুত পদক্ষেপ এবং পরবর্তীতে ফিজিক্যাল থেরাপি টিমের নিবিড় পরিচর্যায় তিন মাস পর তিনি আবারও হাঁটতে সক্ষম হয়েছেন। তার এই ঘুরে দাঁড়ানো অনেকের জন্যই অনুপ্রেরণা।",
        "video_url": "https://youtube.com/watch?v=example3"
    },
    {
        "id": "ps-004",
        "title": "জটিল গর্ভাবস্থায় নিরাপদ মাতৃত্ব: এভারকেয়ারের বিশেষ সাফল্য",
        "patient_name": "Ms. Tania Sultana",
        "city": "Rangamati",
        "doctor_name": "Dr. Shahnaz Parvin",
        "speciality": "Obstetrics & Gynaecology",
        "published_date": "02 February 2026",
        "image": "https://images.unsplash.com/photo-1584515933487-779824d29309?q=80&w=800",
        "content": "উচ্চ রক্তচাপ ও ডায়াবেটিসের কারণে তানিয়া সুলতানার গর্ভাবস্থা ছিল অত্যন্ত ঝুঁকিপূর্ণ। এভারকেয়ারের গাইনি টিমের বিশেষ পর্যবেক্ষণে তিনি একটি সুস্থ সন্তানের জন্ম দিয়েছেন। হাসপাতালের NICU সাপোর্ট এবং দক্ষ নার্সদের সেবা তাকে দুশ্চিন্তামুক্ত থাকতে সাহায্য করেছে।",
        "video_url": ""
    },
    {
        "id": "ps-005",
        "title": "হাঁটু প্রতিস্থাপন সার্জারি: আবার স্বাভাবিক হাঁটাচলার আনন্দ",
        "patient_name": "Mr. Abul Kashem",
        "city": "Chittagong",
        "doctor_name": "Orthopaedics Team",
        "speciality": "Orthopaedics",
        "published_date": "28 December 2025",
        "image": "https://images.unsplash.com/photo-1576091160550-2173dba999ef?q=80&w=800",
        "content": "দীর্ঘ ১০ বছর ধরে হাঁটুর ব্যথায় পঙ্গুপ্রায় ছিলেন আবুল কাশেম সাহেব। এভারকেয়ার চট্টগ্রামে সফল 'টোটাল নী রিপ্লেসমেন্ট' সার্জারির পর তিনি এখন ব্যথামুক্ত এবং লাঠি ছাড়াই চলাফেরা করতে পারছেন। হাসপাতালের উন্নত অপারেশন থিয়েটার ও পরবর্তী কেয়ার তাকে দ্রুত সুস্থ করেছে।",
        "video_url": "https://youtube.com/watch?v=example5"
    },
    {
        "id": "ps-006",
        "title": "ক্যান্সার জয়ী এক যোদ্ধার গল্প",
        "patient_name": "Master Ariful",
        "city": "Comilla",
        "doctor_name": "Oncology Team",
        "speciality": "Oncology",
        "published_date": "10 November 2025",
        "image": "https://images.unsplash.com/photo-1537368910025-700350fe46c7?q=80&w=800",
        "content": "মাত্র ১৫ বছর বয়সে লিম্ফোমায় আক্রান্ত হয় আরিফুল। এভারকেয়ারের অনকোলজি বিভাগের কেমোথেরাপি এবং নিয়মিত কাউন্সেলিং-এর মাধ্যমে সে আজ ক্যান্সার মুক্ত। হাসপাতালের শিশুবান্ধব পরিবেশ তাকে চিকিৎসার কঠিন দিনগুলো পার করতে সাহস যুগিয়েছে।",
        "video_url": ""
    },
    {
        "id": "ps-007",
        "title": "কিডনি ডায়ালাইসিসে নতুন আশা ও সুস্থ জীবন",
        "patient_name": "Mr. Karim Ullah",
        "city": "Anwara",
        "doctor_name": "Nephrology Team",
        "speciality": "Nephrology",
        "published_date": "05 January 2026",
        "image": "https://images.unsplash.com/photo-1579684385127-1ef15d508118?q=80&w=800",
        "content": "ক্রনিক কিডনি ডিজিজে আক্রান্ত করিম সাহেবের কাছে ডায়ালাইসিস ছিল আতঙ্কের নাম। এভারকেয়ারের অত্যাধুনিক ডায়ালাইসিস সেন্টার এবং দক্ষ টেকনিশিয়ানদের সেবায় তিনি এখন নিয়মিত ডায়ালাইসিস নিচ্ছেন এবং কোনো জটিলতা ছাড়াই কাজকর্মে ফিরতে পেরেছেন।",
        "video_url": ""
    },
    {
        "id": "ps-008",
        "title": "জটিল গলব্লাডার অপারেশন: ল্যাপারোস্কোপিক প্রযুক্তির সফল ব্যবহার",
        "patient_name": "Mrs. Nasrin Akter",
        "city": "Chittagong",
        "doctor_name": "General Surgery Team",
        "speciality": "General Surgery",
        "published_date": "12 January 2026",
        "image": "https://images.unsplash.com/photo-1551836022-d5d88e9218df?q=80&w=800",
        "content": "পেটে প্রচণ্ড ব্যথা নিয়ে হাসপাতালে ভর্তি হয়েছিলেন নাসরিন বেগম। পিত্তথলিতে পাথর ধরা পড়লে সার্জনরা ল্যাপারোস্কোপিক পদ্ধতিতে ছোট ছিদ্রের মাধ্যমে অপারেশনটি সম্পন্ন করেন। বড় কোনো কাটা-ছেঁড়া ছাড়াই মাত্র দুই দিনে তিনি বাড়ি ফিরতে পেরেছেন।",
        "video_url": ""
    },
    {
        "id": "ps-009",
        "title": "থাইরয়েড সমস্যা নিয়ন্ত্রণে ফিরে পেলেন প্রাণচাঞ্চল্য",
        "patient_name": "Ms. Ananya Das",
        "city": "Chittagong",
        "doctor_name": "Endocrinology Specialist",
        "speciality": "Endocrinology",
        "published_date": "18 December 2025",
        "image": "https://images.unsplash.com/photo-1594824476967-48c8b964273f?q=80&w=800",
        "content": "শারীরিক দুর্বলতা ও ওজন বৃদ্ধির সমস্যায় ভুগছিলেন অনন্যা। এন্ডোক্রিনোলজি বিভাগের সঠিক রোগ নির্ণয় এবং হরমোন থেরাপির পর তার ক্লান্তি ভাব দূর হয়েছে। এখন তিনি নিয়মিত কর্মক্ষেত্রে যোগ দিচ্ছেন এবং নিজের স্বাস্থ্যের উন্নতি অনুভব করছেন।",
        "video_url": ""
    },
    {
        "id": "ps-010",
        "title": "গ্যাস্ট্রোএন্টারোলজি চিকিৎসায় মুক্তি পেলেন দীর্ঘদিনের পেটের সমস্যা থেকে",
        "patient_name": "Mr. Zahir Raihan",
        "city": "Noakhali",
        "doctor_name": "Gastroenterology Team",
        "speciality": "Gastroenterology",
        "published_date": "22 January 2026",
        "image": "https://images.unsplash.com/photo-1612349317150-e413f6a5b16d?q=80&w=800",
        "content": "দীর্ঘদিনের হজমের সমস্যা ও আলসারে অতিষ্ঠ ছিলেন জহির সাহেব। এন্ডোস্কোপি পরীক্ষার পর ডাক্তারের সঠিক পরামর্শ ও ডায়েট চার্ট অনুসরণ করে তিনি এখন পুরোপুরি সুস্থ। এভারকেয়ারের ডায়াগনস্টিক সার্ভিস তাকে দ্রুত ফল পেতে সাহায্য করেছে।",
        "video_url": ""
    },
    {
        "id": "ps-011",
        "title": "শিশুর শ্রবণশক্তি ফিরে পাওয়া: ইএনটি বিভাগের বড় সাফল্য",
        "patient_name": "Baby Nafisa",
        "city": "Chittagong",
        "doctor_name": "ENT Specialist",
        "speciality": "ENT / Otorhinolaryngology",
        "published_date": "30 January 2026",
        "image": "https://images.unsplash.com/photo-1516627145497-ae6968895b74?q=80&w=800",
        "content": "ছোটবেলা থেকেই নাফিসার কানে শোনার সমস্যা ছিল। ইএনটি স্পেশালিস্টের অধীনে মাইক্রো-সার্জারির পর সে এখন স্বাভাবিকভাবে শুনতে পাচ্ছে। এর ফলে তার পড়াশোনা ও কথা বলার জড়তাও কেটে যাচ্ছে। তার বাবা-মা এভারকেয়ারের প্রতি কৃতজ্ঞতা জানিয়েছেন।",
        "video_url": "https://youtube.com/watch?v=example11"
    },
    {
        "id": "ps-012",
        "title": "চোখের ছানি অপারেশন: আবার ফিরে দেখা সুন্দর পৃথিবী",
        "patient_name": "Mr. Shamim Osman",
        "city": "Chittagong",
        "doctor_name": "Ophthalmology Team",
        "speciality": "Ophthalmology",
        "published_date": "04 February 2026",
        "image": "https://images.unsplash.com/photo-1537368910025-700350fe46c7?q=80&w=800",
        "content": "বার্ধক্যজনিত কারণে চোখে ছানি পড়ে দৃষ্টিশক্তি হারিয়ে ফেলেছিলেন শামিম সাহেব। এভারকেয়ারের অত্যাধুনিক ফ্যাকো (Phaco) সার্জারির মাধ্যমে খুব অল্প সময়ে তার চোখের অপারেশন সম্পন্ন হয়। এখন তিনি স্পষ্টভাবে সবকিছু দেখতে পাচ্ছেন।",
        "video_url": ""
    }
]